jupysec_extension/__init__.py
jupysec_extension/_version.py
jupysec_extension/handlers.py
jupysec_extension/labextension/build_log.json
jupysec_extension/labextension/package.json
jupysec_extension/labextension/static/lib_index_js.7716ec923b3030b6b8ca.js
jupysec_extension/labextension/static/lib_index_js.7716ec923b3030b6b8ca.js.map
jupysec_extension/labextension/static/remoteEntry.4e33f1ed36ff75fadf8f.js
jupysec_extension/labextension/static/remoteEntry.4e33f1ed36ff75fadf8f.js.map
jupysec_extension/labextension/static/style.js
jupysec_extension/labextension/static/style_index_js.7088ee2c7dfcc1491ca5.js
jupysec_extension/labextension/static/style_index_js.7088ee2c7dfcc1491ca5.js.map
jupysec_extension/labextension/static/vendors-node_modules_css-loader_dist_runtime_api_js-node_modules_css-loader_dist_runtime_cssW-72eba1.875eda7a10a8fb14063d.js
jupysec_extension/labextension/static/vendors-node_modules_css-loader_dist_runtime_api_js-node_modules_css-loader_dist_runtime_cssW-72eba1.875eda7a10a8fb14063d.js.map
jupysec_extension/public/1dd56b5b-1c62-4575-974a-3124bdc8f656.html
jupysec_extension/public/README
jupysec_extension/public/score.css
jupysec_extension/public/score.html
jupysec_extension/templates/finding.html
jupysec_extension/templates/index.html
jupysec_extension-0.1.3.data/data/etc/jupyter/jupyter_notebook_config.d/jupysec.json
jupysec_extension-0.1.3.data/data/etc/jupyter/jupyter_server_config.d/jupysec.json
jupysec_extension-0.1.3.data/data/share/jupyter/labextensions/jupysec_extension/build_log.json
jupysec_extension-0.1.3.data/data/share/jupyter/labextensions/jupysec_extension/install.json
jupysec_extension-0.1.3.data/data/share/jupyter/labextensions/jupysec_extension/package.json
jupysec_extension-0.1.3.data/data/share/jupyter/labextensions/jupysec_extension/static/lib_index_js.7716ec923b3030b6b8ca.js
jupysec_extension-0.1.3.data/data/share/jupyter/labextensions/jupysec_extension/static/lib_index_js.7716ec923b3030b6b8ca.js.map
jupysec_extension-0.1.3.dist-info/METADATA
jupysec_extension-0.1.3.dist-info/WHEEL
jupysec_extension-0.1.3.dist-info/top_level.txt
jupysec_extension-0.1.3.dist-info/RECORD
