Metadata-Version: 2.1
Name: jupysec-extension
Version: 0.1.3
Summary: JupyterLab Security Utilities
Home-page: https://github.com/JosephTLucas/jupysec
Author: Joe Lucas
Author-email: joe@joetl.com
License: BSD-3-Clause
Keywords: Jupyter,JupyterLab,JupyterLab3
Platform: Linux
Platform: Mac OS X
Platform: Windows
Classifier: License :: OSI Approved :: BSD License
Classifier: Programming Language :: Python
Classifier: Programming Language :: Python :: 3
Classifier: Programming Language :: Python :: 3.6
Classifier: Programming Language :: Python :: 3.7
Classifier: Programming Language :: Python :: 3.8
Classifier: Programming Language :: Python :: 3.9
Classifier: Framework :: Jupyter
Requires-Python: >=3.6
Requires-Dist: jupyter-server (>=2.0)
